liquidswap_sdk/__init__.py
liquidswap_sdk/client.py
liquidswap_sdk/constants.py
liquidswap_sdk-0.0.2.dist-info/LICENSE
liquidswap_sdk-0.0.2.dist-info/WHEEL
liquidswap_sdk-0.0.2.dist-info/METADATA
liquidswap_sdk-0.0.2.dist-info/RECORD
